jax_tqdm/__init__.py
jax_tqdm/base.py
jax_tqdm/loop_pbar.py
jax_tqdm/py.typed
jax_tqdm/scan_pbar.py
jax_tqdm-0.4.0.dist-info/LICENSE
jax_tqdm-0.4.0.dist-info/METADATA
jax_tqdm-0.4.0.dist-info/WHEEL
jax_tqdm-0.4.0.dist-info/RECORD
