Metadata-Version: 2.1
Name: jax-tqdm
Version: 0.4.0
Summary: Tqdm progress bar for JAX scans and loops
Home-page: https://github.com/jeremiecoullon/jax-tqdm
License: MIT
Keywords: jax,tqdm
Author: Jeremie Coullon
Author-email: jeremie.coullon@gmail.com
Requires-Python: >=3.10,<4.0
Classifier: License :: OSI Approved :: MIT License
Classifier: Programming Language :: Python
Classifier: Programming Language :: Python :: 3
Classifier: Programming Language :: Python :: 3.10
Classifier: Programming Language :: Python :: 3.11
Classifier: Programming Language :: Python :: 3.12
Requires-Dist: chex (>=0.1.87,<0.2.0)
Requires-Dist: jax (>=0.4.12)
Requires-Dist: tqdm (>=4.64.1,<5.0.0)
Project-URL: Repository, https://github.com/jeremiecoullon/jax-tqdm
